[{"uuid": "P_1", "attributes": {"name": {"value": "Lamp", "type": "str"}, "costs": {"value": 100, "type": "int"}, "quality": {"value": 0.73, "type": "float"}}, "references": {"PRODUCT_SPECIFICATION": ["PSP"]}}, {"uuid": "SHOP_FLOOR", "attributes": {}, "references": {"MACHINES": ["PRINTER_1"]}}, {"uuid": "PSS_1", "attributes": {}, "references": {}}, {"uuid": "BATCH", "attributes": {}, "references": {"PRODUCTS": ["P_2", "P_1"]}}, {"uuid": "PSS_2", "attributes": {}, "references": {}}, {"uuid": "PRINTER_1", "attributes": {}, "references": {"TOOLS": [""], "SENSORS": [""]}}, {"uuid": "OPERATOR", "attributes": {}, "references": {}}, {"uuid": "PP_1", "attributes": {}, "references": {}}, {"uuid": "PP_2", "attributes": {}, "references": {}}, {"uuid": "PS_2", "attributes": {}, "references": {"PROCESS_STEP_SPECIFICATION": ["PSS_2"], "PRE_PRODUCT": ["PP_2"], "PREVIOUS": ["OPERATOR"], "TOOL": [""], "SENSOR_READINGS": ["COM-APIRadian/COM-MobileEntities/COM-Target/MEA-Position@2025-07-14T08:50:36.470909"], "MACHINE": ["PRINTER_1"]}}, {"uuid": "P_2", "attributes": {}, "references": {"PRODUCT_SPECIFICATION": ["PSP"]}}, {"uuid": "PS_1", "attributes": {}, "references": {"PROCESS_STEP_SPECIFICATION": ["PSS_1"], "PRE_PRODUCT": ["PP_1"], "NEXT": ["PS_2"], "PREVIOUS": ["OPERATOR"], "TOOL": [""], "SENSOR_READINGS": ["COM-APIRadian/COM-MobileEntities/COM-Target/MEA-Position@2025-07-14T08:50:36.470909"], "MACHINE": ["PRINTER_1"]}}, {"uuid": "PSP", "attributes": {}, "references": {}}]